spinachlang/__init__.py
spinachlang/__main__.py
spinachlang/ast_builder.py
spinachlang/backend.py
spinachlang/exit_code.py
spinachlang/grammar.lark
spinachlang/main.py
spinachlang/parser.py
spinachlang/spinach.py
spinachlang/spinach_types.py
spinachlang-0.2.3.dist-info/licenses/LICENSE
spinachlang-0.2.3.dist-info/METADATA
spinachlang-0.2.3.dist-info/WHEEL
spinachlang-0.2.3.dist-info/entry_points.txt
spinachlang-0.2.3.dist-info/top_level.txt
spinachlang-0.2.3.dist-info/RECORD
